detect_droid-0.2.18.dist-info/licenses/LICENSE
detect_droid-0.2.18.dist-info/licenses/NOTICE
droid/__init__.py
droid/__main__.py
droid/abstracts.py
droid/color.py
droid/convert.py
droid/export.py
droid/integrity.py
droid/list.py
droid/search.py
droid/validate.py
droid/platforms/__init__.py
droid/platforms/common.py
droid/platforms/elastic.py
droid/platforms/ms_xdr.py
droid/platforms/sentinel.py
droid/platforms/splunk.py
droid/sources/__init__.py
droid/sources/sigmahq.py
detect_droid-0.2.18.dist-info/METADATA
detect_droid-0.2.18.dist-info/WHEEL
detect_droid-0.2.18.dist-info/entry_points.txt
detect_droid-0.2.18.dist-info/top_level.txt
detect_droid-0.2.18.dist-info/RECORD
