Metadata-Version: 2.4
Name: detect-droid
Version: 0.2.18
Summary: Detection Rules Optimisation Integration Deployment
Home-page: https://github.com/certeu/droid
Author: cert-eu/mlc
Author-email: services@cert.europa.eu
License: "EUPL-1.2"
Requires-Python: >=3.11.8
License-File: LICENSE
License-File: NOTICE
Requires-Dist: PyYAML==6.0.1
Requires-Dist: pySigma==0.11.23
Requires-Dist: ruamel.yaml==0.18.1
Requires-Dist: azure-common==1.1.28
Requires-Dist: azure-core==1.30.1
Requires-Dist: azure-identity==1.16.1
Requires-Dist: azure-mgmt-core==1.4.0
Requires-Dist: azure-mgmt-monitor==6.0.2
Requires-Dist: azure-mgmt-resource==23.0.1
Requires-Dist: azure-mgmt-resourcegraph==8.0.0
Requires-Dist: azure-mgmt-securityinsight==2.0.0b2
Requires-Dist: azure-monitor-query==1.4.1
Requires-Dist: splunk-sdk==2.0.1
Requires-Dist: colorama==0.4.6
Requires-Dist: python-json-logger==2.0.7
Requires-Dist: requests==2.32.3
Requires-Dist: elasticsearch==8.14.0
Dynamic: license-file
